krholidays/__init__.py
krholidays/constants.py
krholidays/holiday_base.py
krholidays/utils.py
krholidays/countries/__init__.py
krholidays/countries/korea.py
korean_holiday_calendar-1.0.1.dist-info/LICENSE
korean_holiday_calendar-1.0.1.dist-info/METADATA
korean_holiday_calendar-1.0.1.dist-info/WHEEL
korean_holiday_calendar-1.0.1.dist-info/top_level.txt
korean_holiday_calendar-1.0.1.dist-info/RECORD
