Metadata-Version: 2.1
Name: korean-holiday-calendar
Version: 1.0.1
Summary: korean-specialized holiday calendar based on [python-holidays] package by dr-prodigy
Home-page: https://github.com/rabbitcarrot20/korean-holiday-calendar
Author: rabbitcarrot20, gadarangeo
Author-email: butterfly36082@gmail.com, yuuhy1020@gmail.com
License: UNKNOWN
Project-URL: Homepage 2, https://github.com/gadarangeo/korean-holiday-calendar
Platform: UNKNOWN
Classifier: Programming Language :: Python :: 3
Classifier: License :: OSI Approved :: MIT License
Classifier: Operating System :: OS Independent
License-File: LICENSE
